integration/__init__.py
integration/test_archive_scenarios.py
integration/test_passing_config_directly.py
integration/test_pyfdb.py
pyfdb/__init__.py
pyfdb/processed_fdb.h
pyfdb/pyfdb.py
pyfdb/version.py
pyfdb-0.1.2.dist-info/licenses/LICENSE.txt
unit/__init__.py
unit/test_archive.py
pyfdb-0.1.2.dist-info/METADATA
pyfdb-0.1.2.dist-info/WHEEL
pyfdb-0.1.2.dist-info/top_level.txt
pyfdb-0.1.2.dist-info/RECORD
