Metadata-Version: 2.4
Name: pyfdb
Version: 0.1.2
Summary: Python interface to FDB
Author-email: "European Centre for Medium-Range Weather Forecasts (ECMWF)" <software.support@ecmwf.int>
Project-URL: Documentation, https://github.com/ecmwf/pyfdb
Project-URL: Homepage, https://github.com/ecmwf/pyfdb
Project-URL: Issues, https://github.com/ecmwf/pyfdb/issues
Project-URL: Repository, https://github.com/ecmwf/pyfdb
Keywords: python,fdb,tools
Requires-Python: >=3.9
License-File: LICENSE.txt
Requires-Dist: cffi
Requires-Dist: findlibs
Requires-Dist: eccodes>=2.39.1
Requires-Dist: packaging
Provides-Extra: test
Requires-Dist: pytest; extra == "test"
Requires-Dist: pytest-cov; extra == "test"
Requires-Dist: pytest-flakes; extra == "test"
Requires-Dist: gitpython; extra == "test"
Provides-Extra: dev
Requires-Dist: isort; extra == "dev"
Requires-Dist: black; extra == "dev"
Requires-Dist: flake8; extra == "dev"
Requires-Dist: tox>=4.19; extra == "dev"
Dynamic: license-file
